mod_io_downloader/__init__.py
mod_io_downloader/__main__.py
mod_io_downloader/app_config.py
mod_io_downloader/game_config_parser.py
mod_io_downloader/mod_io.py
mod_io_downloader/models.py
mod_io_downloader-1.0.4.dist-info/METADATA
mod_io_downloader-1.0.4.dist-info/WHEEL
mod_io_downloader-1.0.4.dist-info/licenses/LICENSE
mod_io_downloader-1.0.4.dist-info/RECORD
