Metadata-Version: 2.4
Name: mod_io_downloader
Version: 1.0.4
Summary: Downloads mods faster than mod.io plugin (for Mordhau Server)
Project-URL: Homepage, https://github.com/ColdSpirit0/mod_io_downloader
Project-URL: Issues, https://github.com/ColdSpirit0/mod_io_downloader/issues
Author: ColdSpirit
License:                     GNU AFFERO GENERAL PUBLIC LICENSE
License-File: LICENSE
Classifier: License :: OSI Approved :: GNU Affero General Public License v3
Classifier: Operating System :: OS Independent
Classifier: Programming Language :: Python :: 3
Requires-Python: >=3.12
Requires-Dist: annotated-types==0.7.0
Requires-Dist: certifi==2025.4.26
Requires-Dist: charset-normalizer==3.4.2
Requires-Dist: click==8.1.7
Requires-Dist: idna==3.10
Requires-Dist: pathvalidate==3.2.0
Requires-Dist: pydantic-core==2.33.2
Requires-Dist: pydantic==2.11.5
Requires-Dist: requests==2.31.0
Requires-Dist: setuptools==80.9.0
Requires-Dist: termcolor==2.4.0
Requires-Dist: tqdm==4.66.2
Requires-Dist: typing-extensions==4.14.0
Requires-Dist: typing-inspection==0.4.1
Requires-Dist: unreal-ini-parser==1.0.2
Requires-Dist: urllib3==2.4.0
Requires-Dist: wheel==0.45.1
